gagrab
