Metadata-Version: 1.1
Name: gagrab
Version: 0.2.0
Summary: When want to grab your data from Google Analytics: gagrab it.
Home-page: https://github.com/ambitioninc/gagrab
Author: Erik Swanson
Author-email: opensource@ambition.com
License: MIT
Platform: UNKNOWN
Classifier: Programming Language :: Python :: 2.7
Classifier: Programming Language :: Python :: 3.2
Classifier: Programming Language :: Python :: 3.3
Classifier: Intended Audience :: Developers
Classifier: License :: OSI Approved :: MIT License
Classifier: Operating System :: OS Independent
